LICENSE
MANIFEST.in
README.rst
VERSION
setup.py
browser/__init__.py
django_brython/__init__.py
django_brython/apps.py
django_brython/middleware.py
django_brython/mock_testing.py
django_brython/models.py
django_brython/staticfiles.py
django_brython/testing.py
django_brython/urls.py
django_brython/views.py
django_brython.egg-info/PKG-INFO
django_brython.egg-info/SOURCES.txt
django_brython.egg-info/dependency_links.txt
django_brython.egg-info/top_level.txt
django_brython/brython/__init__.py
django_brython/brython/make_package.py
django_brython/brython/python_minifier.py
django_brython/static/django_brython/js/brython.js
django_brython/static/django_brython/js/brython_stdlib.js