Metadata-Version: 2.1
Name: django-brython
Version: 1.5.4
Summary: Django - Brython bindings
Home-page: https://django-brython.lovasb.com/
Author: Bence Lovas
Author-email: me@lovasb.com
License: UNKNOWN
Project-URL: Documentation, https://django-brython.lovasb.com/
Project-URL: Source, https://gitlab.com/lovasb/django-brython
Project-URL: Tracker, https://gitlab.com/lovasb/django-brython/-/issues
Platform: UNKNOWN
Classifier: Environment :: Web Environment
Classifier: Framework :: Django
Classifier: Intended Audience :: Developers
Classifier: License :: OSI Approved :: MIT License
Classifier: Operating System :: OS Independent
Classifier: Programming Language :: Python
Classifier: Programming Language :: Python :: 3
Classifier: Programming Language :: Python :: 3 :: Only
Classifier: Topic :: Internet :: WWW/HTTP
Classifier: Topic :: Internet :: WWW/HTTP :: Dynamic Content
Classifier: Topic :: Software Development :: Libraries :: Python Modules
